kolonix_rag/__init__.py
kolonix_rag/kolonix_rag.py
kolonix_rag-0.1.1.dist-info/METADATA
kolonix_rag-0.1.1.dist-info/WHEEL
kolonix_rag-0.1.1.dist-info/top_level.txt
kolonix_rag-0.1.1.dist-info/RECORD
