Metadata-Version: 2.1
Name: kolonix-rag
Version: 0.1.1
Summary: A Retrieval-Augmented Generation (RAG) framework with MongoDB and Sentence Transformers
Home-page: https://github.com/kolonixid/kolonix-rag
Author: Rino Alfian
Author-email: rino.alpin@gmail.com
Classifier: Programming Language :: Python :: 3
Classifier: License :: OSI Approved :: MIT License
Classifier: Operating System :: OS Independent
Requires-Python: >=3.6
Requires-Dist: pymongo
Requires-Dist: sentence-transformers
Requires-Dist: nltk
Requires-Dist: numpy
